[{"domain":"11st.co.kr","rankInCountry":22,"country":"South Korea","appDomain":"11st.app","price":"NT$489"},{"domain":"58b.tv","rankInCountry":42,"country":"Taiwan","appDomain":"58b.app","price":"NT$489"},{"domain":"Aastocks.com","rankInCountry":12,"country":"Hong Kong","appDomain":"aastocks.app","price":"NT$489"},{"domain":"Afreecatv.com","rankInCountry":27,"country":"South Korea","appDomain":"afreecatv.app","price":"NT$489"},{"domain":"Ameblo.jp","rankInCountry":15,"country":"Japan","appDomain":"ameblo.app","price":"NT$489"},{"domain":"Appledaily.com","rankInCountry":13,"country":"Hong Kong","appDomain":"appledaily.app","price":"NT$489"},{"domain":"Appledaily.com","rankInCountry":24,"country":"Taiwan","appDomain":"appledaily.app","price":"NT$489"},{"domain":"Bastillepost.com","rankInCountry":11,"country":"Hong Kong","appDomain":"bastillepost.app","price":"NT$489"},{"domain":"Beautyexchange.com.hk","rankInCountry":31,"country":"Hong Kong","appDomain":"beautyexchange.app","price":"NT$489"},{"domain":"Bldaily.com","rankInCountry":13,"country":"Taiwan","appDomain":"bldaily.app","price":"NT$489"},{"domain":"Bldaily.com","rankInCountry":37,"country":"Hong Kong","appDomain":"bldaily.app","price":"NT$489"},{"domain":"Bongacams.com","rankInCountry":44,"country":"Singapore","appDomain":"bongacams.app","price":"NT$489"},{"domain":"Businessweekly.com.tw","rankInCountry":40,"country":"Taiwan","appDomain":"businessweekly.app","price":"NT$489"},{"domain":"Channelnewsasia.com","rankInCountry":38,"country":"Singapore","appDomain":"channelnewsasia.app","price":"NT$489"},{"domain":"Chatwork.com","rankInCountry":50,"country":"Japan","appDomain":"chatwork.app","price":"NT$489"},{"domain":"Chinadaily.com.cn","rankInCountry":38,"country":"China","appDomain":"chinadaily.app","price":"NT$489"},{"domain":"Chosun.com","rankInCountry":42,"country":"South Korea","appDomain":"chosun.app","price":"NT$489"},{"domain":"Ci123.com","rankInCountry":46,"country":"China","appDomain":"ci123.app","price":"NT$489"},{"domain":"Ck101.com","rankInCountry":18,"country":"Taiwan","appDomain":"ck101.app","price":"NT$489"},{"domain":"Clien.net","rankInCountry":25,"country":"South Korea","appDomain":"clien.app","price":"NT$489"},{"domain":"Cnblogs.com","rankInCountry":40,"country":"China","appDomain":"cnblogs.app","price":"NT$489"},{"domain":"Dailymotion.com","rankInCountry":44,"country":"Japan","appDomain":"dailymotion.app","price":"NT$1,929"},{"domain":"Danawa.com","rankInCountry":31,"country":"South Korea","appDomain":"danawa.app","price":"NT$489"},{"domain":"Daum.net","rankInCountry":5,"country":"South Korea","appDomain":"daum.app","price":"NT$489"},{"domain":"Dcfever.com","rankInCountry":18,"country":"Hong Kong","appDomain":"dcfever.app","price":"NT$489"},{"domain":"Dcinside.com","rankInCountry":28,"country":"South Korea","appDomain":"dcinside.app","price":"NT$489"},{"domain":"Deloton.com","rankInCountry":46,"country":"Singapore","appDomain":"deloton.app","price":"NT$489"},{"domain":"Diply.com","rankInCountry":17,"country":"United States","appDomain":"diply.app","price":"NT$489"},{"domain":"Donga.com","rankInCountry":19,"country":"South Korea","appDomain":"donga.app","price":"NT$489"},{"domain":"Doorblog.jp","rankInCountry":41,"country":"Japan","appDomain":"doorblog.app","price":"NT$489"},{"domain":"Eastday.com","rankInCountry":37,"country":"China","appDomain":"eastday.app","price":"NT$489"},{"domain":"Ebc.net.tw","rankInCountry":15,"country":"Taiwan","appDomain":"ebc.app","price":"NT$489"},{"domain":"Epochtimes.com","rankInCountry":28,"country":"Taiwan","appDomain":"epochtimes.app","price":"NT$489"},{"domain":"Epochtimes.com","rankInCountry":33,"country":"Hong Kong","appDomain":"epochtimes.app","price":"NT$489"},{"domain":"Etnet.com.hk","rankInCountry":19,"country":"Hong Kong","appDomain":"etnet.app","price":"NT$489"},{"domain":"Etorrent.co.kr","rankInCountry":36,"country":"South Korea","appDomain":"etorrent.app","price":"NT$489"},{"domain":"Ettoday.net","rankInCountry":32,"country":"Hong Kong","appDomain":"ettoday.app","price":"NT$489"},{"domain":"Ettoday.net","rankInCountry":6,"country":"Taiwan","appDomain":"ettoday.app","price":"NT$489"},{"domain":"Eyny.com","rankInCountry":21,"country":"Taiwan","appDomain":"eyny.app","price":"NT$489"},{"domain":"Fc2.com","rankInCountry":11,"country":"Japan","appDomain":"fc2.app","price":"NT$489"},{"domain":"Feebee.com.tw","rankInCountry":39,"country":"Taiwan","appDomain":"feebee.app","price":"NT$489"},{"domain":"Gmw.cn","rankInCountry":27,"country":"China","appDomain":"gmw.app","price":"NT$489"},{"domain":"Goo.ne.jp","rankInCountry":29,"country":"Japan","appDomain":"goo.app","price":"NT$489"},{"domain":"Hangseng.com","rankInCountry":36,"country":"Hong Kong","appDomain":"hangseng.app","price":"NT$489"},{"domain":"Hardwarezone.com.sg","rankInCountry":27,"country":"Singapore","appDomain":"hardwarezone.app","price":"NT$489"},{"domain":"Hatena.ne.jp","rankInCountry":45,"country":"Japan","appDomain":"hatena.app","price":"NT$489"},{"domain":"Hatenablog.com","rankInCountry":46,"country":"Japan","appDomain":"hatenablog.app","price":"NT$489"},{"domain":"Hkgolden.com","rankInCountry":15,"country":"Hong Kong","appDomain":"hkgolden.app","price":"NT$489"},{"domain":"Hkjc.com","rankInCountry":42,"country":"Hong Kong","appDomain":"hkjc.app","price":"NT$489"},{"domain":"Huanqiu.com","rankInCountry":39,"country":"China","appDomain":"huanqiu.app","price":"NT$489"},{"domain":"Ilbe.com","rankInCountry":40,"country":"South Korea","appDomain":"ilbe.app","price":"NT$489"},{"domain":"Interpark.com","rankInCountry":46,"country":"South Korea","appDomain":"interpark.app","price":"NT$489"},{"domain":"Inven.co.kr","rankInCountry":15,"country":"South Korea","appDomain":"inven.app","price":"NT$489"},{"domain":"Japanpost.jp","rankInCountry":43,"country":"Japan","appDomain":"japanpost.app","price":"NT$489"},{"domain":"Jobstreet.com.sg","rankInCountry":39,"country":"Singapore","appDomain":"jobstreet.app","price":"NT$489"},{"domain":"Joins.com","rankInCountry":41,"country":"South Korea","appDomain":"joins.app","price":"NT$489"},{"domain":"K618.cn","rankInCountry":25,"country":"China","appDomain":"k618.app","price":"NT$489"},{"domain":"Kakaku.com","rankInCountry":14,"country":"Japan","appDomain":"kakaku.app","price":"NT$489"},{"domain":"Kknews.cc","rankInCountry":47,"country":"Taiwan","appDomain":"kknews.app","price":"NT$489"},{"domain":"Lifedaily.com","rankInCountry":32,"country":"United States","appDomain":"lifedaily.app","price":"NT$489"},{"domain":"Lihkg.com","rankInCountry":17,"country":"Hong Kong","appDomain":"lihkg.app","price":"NT$489"},{"domain":"Liontravel.com","rankInCountry":48,"country":"Taiwan","appDomain":"liontravel.app","price":"NT$489"},{"domain":"Livedoor.com","rankInCountry":17,"country":"Japan","appDomain":"livedoor.app","price":"NT$489"},{"domain":"Livedoor.jp","rankInCountry":20,"country":"Japan","appDomain":"livedoor.app","price":"NT$489"},{"domain":"Ltn.com.tw","rankInCountry":9,"country":"Taiwan","appDomain":"ltn.app","price":"NT$489"},{"domain":"Marumaru.in","rankInCountry":29,"country":"South Korea","appDomain":"marumaru.app","price":"NT$489"},{"domain":"Menclub.hk","rankInCountry":26,"country":"Hong Kong","appDomain":"menclub.app","price":"NT$489"},{"domain":"Microsoftonline.com","rankInCountry":16,"country":"United States","appDomain":"microsoftonline.app","price":"NT$489"},{"domain":"Microsoftonline.com","rankInCountry":22,"country":"Singapore","appDomain":"microsoftonline.app","price":"NT$489"},{"domain":"Mobile01.com","rankInCountry":20,"country":"Taiwan","appDomain":"mobile01.app","price":"NT$489"},{"domain":"Momoshop.com.tw","rankInCountry":11,"country":"Taiwan","appDomain":"momoshop.app","price":"NT$489"},{"domain":"Namu.wiki","rankInCountry":12,"country":"South Korea","appDomain":"namu.app","price":"NT$489"},{"domain":"Nate.com","rankInCountry":26,"country":"South Korea","appDomain":"nate.app","price":"NT$489"},{"domain":"Nicovideo.jp","rankInCountry":8,"country":"Japan","appDomain":"nicovideo.app","price":"NT$489"},{"domain":"Nonno.hk","rankInCountry":24,"country":"Hong Kong","appDomain":"nonno.app","price":"NT$489"},{"domain":"Nownews.com","rankInCountry":8,"country":"Taiwan","appDomain":"nownews.app","price":"NT$489"},{"domain":"Ntd.tv","rankInCountry":37,"country":"Singapore","appDomain":"ntd.app","price":"NT$489"},{"domain":"Ntu.edu.sg","rankInCountry":32,"country":"Singapore","appDomain":"ntu.app","price":"NT$489"},{"domain":"Nus.edu.sg","rankInCountry":26,"country":"Singapore","appDomain":"nus.app","price":"NT$489"},{"domain":"Ocbc.com","rankInCountry":35,"country":"Singapore","appDomain":"ocbc.app","price":"NT$489"},{"domain":"Pages.tmall.com","rankInCountry":16,"country":"China","appDomain":"pages.app","price":"NT$14,841"},{"domain":"People.com.cn","rankInCountry":48,"country":"China","appDomain":"people.app","price":"NT$14,841"},{"domain":"Pixnet.net","rankInCountry":9,"country":"Hong Kong","appDomain":"pixnet.app","price":"NT$489"},{"domain":"Pixnet.net","rankInCountry":3,"country":"Taiwan","appDomain":"pixnet.app","price":"NT$489"},{"domain":"Plurk.com","rankInCountry":46,"country":"Taiwan","appDomain":"plurk.app","price":"NT$489"},{"domain":"Ppomppu.co.kr","rankInCountry":20,"country":"South Korea","appDomain":"ppomppu.app","price":"NT$489"},{"domain":"Presslogic.com","rankInCountry":22,"country":"Hong Kong","appDomain":"presslogic.app","price":"NT$489"},{"domain":"Providr.com","rankInCountry":39,"country":"United States","appDomain":"providr.app","price":"NT$489"},{"domain":"Rednet.cn","rankInCountry":43,"country":"China","appDomain":"rednet.app","price":"NT$489"},{"domain":"Ruliweb.com","rankInCountry":16,"country":"South Korea","appDomain":"ruliweb.app","price":"NT$489"},{"domain":"Setn.com","rankInCountry":10,"country":"Taiwan","appDomain":"setn.app","price":"NT$489"},{"domain":"Singpass.gov.sg","rankInCountry":23,"country":"Singapore","appDomain":"singpass.app","price":"NT$489"},{"domain":"Stackoverflow.com","rankInCountry":36,"country":"United States","appDomain":"stackoverflow.app","price":"NT$489"},{"domain":"Straitstimes.com","rankInCountry":18,"country":"Singapore","appDomain":"straitstimes.app","price":"NT$489"},{"domain":"T.co","rankInCountry":23,"country":"United States","appDomain":"t.app","price":"NT$59,366"},{"domain":"Tabelog.com","rankInCountry":47,"country":"Japan","appDomain":"tabelog.app","price":"NT$489"},{"domain":"Techbang.com","rankInCountry":45,"country":"Taiwan","appDomain":"techbang.app","price":"NT$489"},{"domain":"Theepochtimes.com","rankInCountry":45,"country":"Singapore","appDomain":"theepochtimes.app","price":"NT$489"},{"domain":"Thepiratebay.org","rankInCountry":41,"country":"Singapore","appDomain":"thepiratebay.app","price":"NT$489"},{"domain":"Tistory.com","rankInCountry":14,"country":"South Korea","appDomain":"tistory.app","price":"NT$489"},{"domain":"Todayhumor.co.kr","rankInCountry":49,"country":"South Korea","appDomain":"todayhumor.app","price":"NT$489"},{"domain":"Tvbs.com.tw","rankInCountry":14,"country":"Taiwan","appDomain":"tvbs.app","price":"NT$489"},{"domain":"Txxx.com","rankInCountry":29,"country":"Singapore","appDomain":"txxx.app","price":"NT$489"},{"domain":"Udn.com","rankInCountry":23,"country":"Taiwan","appDomain":"udn.app","price":"NT$489"},{"domain":"Unwire.hk","rankInCountry":28,"country":"Hong Kong","appDomain":"unwire.app","price":"NT$489"},{"domain":"Uwants.com","rankInCountry":39,"country":"Hong Kong","appDomain":"uwants.app","price":"NT$489"},{"domain":"Wasabisyrup.com","rankInCountry":34,"country":"South Korea","appDomain":"wasabisyrup.app","price":"NT$489"},{"domain":"Weblio.jp","rankInCountry":34,"country":"Japan","appDomain":"weblio.app","price":"NT$489"},{"domain":"Xuite.net","rankInCountry":41,"country":"Taiwan","appDomain":"xuite.app","price":"NT$489"},{"domain":"Youth.cn","rankInCountry":34,"country":"China","appDomain":"youth.app","price":"NT$7,421"},{"domain":"Zi.media","rankInCountry":49,"country":"Taiwan","appDomain":"zi.app","price":"NT$29,683"}]